marathon/__init__.py
marathon/__main__.py
marathon/cached.py
marathon/cli.py
marathon/cli_parser.py
marathon/gcloud.py
marathon/utils.py
marathon/version.py
run_marathon-0.3.2.dist-info/LICENSE
run_marathon-0.3.2.dist-info/METADATA
run_marathon-0.3.2.dist-info/WHEEL
run_marathon-0.3.2.dist-info/entry_points.txt
run_marathon-0.3.2.dist-info/top_level.txt
run_marathon-0.3.2.dist-info/RECORD
