Metadata-Version: 2.1
Name: run-marathon
Version: 0.3.2
Summary: Simplify and manage your serverless container deployments. Like docker-compose but for Cloud Run.
Home-page: https://github.com/adrianchifor/run-marathon
Author: Adrian Chifor
Author-email: me@adrianchifor.com
License: Apache License 2.0
Keywords: cloud run build deploy containers kubernetes knative
Classifier: Development Status :: 4 - Beta
Classifier: Intended Audience :: Developers
Classifier: Topic :: Software Development :: Build Tools
Classifier: Topic :: System :: Distributed Computing
Classifier: License :: OSI Approved :: Apache Software License
Classifier: Programming Language :: Python :: 3.6
Classifier: Programming Language :: Python :: 3.7
Requires-Python: >=3.6
License-File: LICENSE
Requires-Dist: pyyaml
Requires-Dist: toposort
